<?xml version="1.0" encoding="utf-8"?>
<!DOCTYPE hibernate-mapping PUBLIC "-//Hibernate/Hibernate Mapping DTD 3.0//EN"
"http://hibernate.sourceforge.net/hibernate-mapping-3.0.dtd">
<!-- 
    Mapping file autogenerated by MyEclipse Persistence Tools
-->
<hibernate-mapping>
    <class name="com.cnarj.ttxs.pojo.user.MemberAddInfo" table="TTXS_USER_MEMBERADDINFO" schema="TTXSCNARJ">
        <comment>系统会员附加信息表</comment>
        <id name="addinfoid" type="java.lang.String">
            <column name="ADDINFOID" length="32" />
            <generator class="uuid"></generator>
        </id>
        
        <many-to-one name="member" class="com.cnarj.ttxs.pojo.user.Member" fetch="select">
            <column name="MEMBERID" length="32" />
        </many-to-one>
        <property name="phone" type="java.lang.String">
            <column name="PHONE" length="20" />
        </property>
        <property name="inaddr" type="java.lang.String">
            <column name="INADDR" length="128" />
        </property>
        <property name="realname" type="java.lang.String">
            <column name="REALNAME" length="64" />
        </property>
        <property name="childname" type="java.lang.String">
            <column name="CHILDNAME" length="20" />
        </property>
        <property name="school" type="java.lang.String">
            <column name="SCHOOL" length="128" />
        </property>
        <property name="grade" type="java.lang.String">
            <column name="GRADE" length="20" />
        </property>
        <property name="classes" type="java.lang.String">
            <column name="CLASSES" length="20" />
        </property>
        <property name="postoffice" type="java.lang.String">
            <column name="POSTOFFICE" length="128" />
        </property>
        <property name="mage" type="java.lang.Long">
            <column name="MAGE" precision="22" scale="0" />
        </property>
     	 <property name="sex" type="java.lang.String">
            <column name="SEX" length="2" />
        </property>
        <property name="identity" type="java.lang.String">
        	<column name="IDENTITY" length="10"/>
        </property>
    </class>
</hibernate-mapping>
