<?xml version="1.0" encoding="utf-8"?>
<!DOCTYPE hibernate-mapping PUBLIC "-//Hibernate/Hibernate Mapping DTD 3.0//EN"
"http://hibernate.sourceforge.net/hibernate-mapping-3.0.dtd">
<!-- 
    Mapping file autogenerated by MyEclipse Persistence Tools
-->
<hibernate-mapping>
    <class name="com.cnarj.ttxs.pojo.stuz.blogaction" table="TTXS_STUZ_BLOGACTION" schema="TTXSCNARJ">
        <comment>博文处理记录(阅读)表 记录博文被浏览等情况</comment>
        <id name="actionid" type="java.lang.String">
            <column name="ACTIONID" length="32" />
            <generator class="uuid"></generator>
        </id>
        <many-to-one name="blog" class="com.cnarj.ttxs.pojo.stuz.Blog" fetch="select">
            <column name="BLOGID" length="32">
                <comment>被浏览博文的ID</comment>
            </column>
        </many-to-one>
        <many-to-one name="member" class="com.cnarj.ttxs.pojo.user.Member" fetch="select">
            <column name="MEMBERID" length="32">
            <comment>浏览或其他处理者的用户ID</comment>
            </column>
        </many-to-one>
        <property name="actiontype" type="java.lang.Long">
            <column name="ACTIONTYPE" precision="22" scale="0">
                <comment>1 浏览</comment>
            </column>
        </property>
        <property name="actiondate" type="java.util.Date">
            <column name="ACTIONDATE" length="7" />
        </property>
        <property name="userip" type="java.lang.String">
            <column name="USERIP" length="256" />
        </property>
        <property name="username" type="java.lang.String">
            <column name="USERNAME" length="128" />
        </property>
    </class>
</hibernate-mapping>
