<?xml version="1.0" encoding="utf-8"?>
<!DOCTYPE hibernate-mapping PUBLIC "-//Hibernate/Hibernate Mapping DTD 3.0//EN"
"http://hibernate.sourceforge.net/hibernate-mapping-3.0.dtd">
<!-- 
	Mapping file autogenerated by MyEclipse Persistence Tools
-->
<hibernate-mapping>
	<class name="com.cnarj.ttxs.pojo.interest.Activity"
		table="TTXS_INT_ACTIVITY" schema="TTXSCNARJ">
		<id name="activityid" type="java.lang.String">
			<column name="ACTIVITYID" length="32" />
			<generator class="uuid"></generator>
		</id>
		<property name="activitytitle" type="java.lang.String">
			<column name="ACTIVITYTITLE" length="256" />
		</property>
		<property name="activityintro"
			type="org.springframework.orm.hibernate3.support.ClobStringType">
			<column name="ACTIVITYINTRO" length="1048576000" />
		</property>
		<property name="activitysrc" type="java.lang.String">
			<column name="ACTIVITYSRC" length="256" />
		</property>
		<property name="createdate" type="java.util.Date">
			<column name="CREATEDATE" length="7" />
		</property>
		<property name="modifydate" type="java.util.Date">
			<column name="MODIFYDATE" length="7" />
		</property>
		<property name="begindate" type="java.util.Date">
			<column name="BEGINDATE" length="7" />
		</property>
		<property name="enddate" type="java.util.Date">
			<column name="ENDDATE" length="7" />
		</property>
		<property name="isshowpic" type="java.lang.String">
			<column name="ISSHOWPIC" length="1" />
		</property>
		<property name="sysnotesid" type="java.lang.String">
			<column name="SYSNOTESID" length="32" />
		</property>
		<property name="industryid" type="java.lang.String">
			<column name="INDUSTRYID" length="32" />
		</property>
		<property name="unlinepath" type="java.lang.String">
			<column name="UNLINEPATH" length="256" />
		</property>
		<property name="activetypeid" type="java.lang.String">
			<column name="ACTIVETYPEID" length="32" />
		</property>
		<many-to-one name="programa"
			class="com.cnarj.ttxs.pojo.interest.ActivityPrograma"
			fetch="select">
			<column name="PRO_ID" length="32" />
		</many-to-one>
		<many-to-one name="activityType"
			class="com.cnarj.ttxs.pojo.interest.ActivityType" fetch="select">
			<column name="TYPE_ID" length="32" />
		</many-to-one>
		<set name="activityTeachers" inverse="true">
			<key>
				<column name="ACTIVITYID" length="32" />
			</key>
			<one-to-many
				class="com.cnarj.ttxs.pojo.interest.ActivityTeacher" />
		</set>
		<set name="activityWorkses" inverse="true">
			<key>
				<column name="ACTIVITYID" length="32" />
			</key>
			<one-to-many
				class="com.cnarj.ttxs.pojo.interest.ActivityWorks" />
		</set>


		<property name="activitycode" type="java.lang.String">
			<column name="ACTIVITYCODE" length="32" />
		</property>
		<property name="activitySeq" type="java.lang.Long">
			<column name="ACTIVITYSEQ" precision="22" scale="0" />
		</property>
		<property name="activityfeaphotopath" type="java.lang.String">
			<column name="ACTIVITYFEAPHOTOPATH" length="256" />
		</property>
		
		<property name="activityrule"
			type="org.springframework.orm.hibernate3.support.ClobStringType">
			<column name="ACTIVITYRULE" length="1048576000" />
		</property>
	</class>
</hibernate-mapping>
